django_master_password-1.1.1.dist-info/DESCRIPTION.rst
django_master_password-1.1.1.dist-info/METADATA
django_master_password-1.1.1.dist-info/RECORD
django_master_password-1.1.1.dist-info/WHEEL
django_master_password-1.1.1.dist-info/metadata.json
django_master_password-1.1.1.dist-info/top_level.txt
master_password/__init__.py
master_password/apps.py
master_password/auth.py
master_password/management/__init__.py
master_password/management/commands/__init__.py
master_password/management/commands/make_password.py
master_password/tests/__init__.py
master_password/tests/settings.py
master_password/tests/tests.py
